{
  "filePath" : "/home/maryam/clearblue/files/android-source-30/android/wm/WindowAddRemovePerfTest.java",
  "packageName" : "android.wm",
  "className" : "TestWindow",
  "comment" : "",
  "variables" : [ {
    "name" : "mLayoutParams",
    "type" : "WindowManager.LayoutParams",
    "comment" : "",
    "links" : [ ]
  }, {
    "name" : "mOutFrame",
    "type" : "Rect",
    "comment" : "",
    "links" : [ ]
  }, {
    "name" : "mOutContentInsets",
    "type" : "Rect",
    "comment" : "",
    "links" : [ ]
  }, {
    "name" : "mOutStableInsets",
    "type" : "Rect",
    "comment" : "",
    "links" : [ ]
  }, {
    "name" : "mOutDisplayCutout",
    "type" : "DisplayCutout.ParcelableWrapper",
    "comment" : "",
    "links" : [ ]
  }, {
    "name" : "mOutInsetsState",
    "type" : "InsetsState",
    "comment" : "",
    "links" : [ ]
  }, {
    "name" : "mOutControls",
    "type" : "InsetsSourceControl[]",
    "comment" : "",
    "links" : [ ]
  } ],
  "methods" : [ {
    "name" : " void runBenchmark(ManualBenchmarkState state) throws RemoteException",
    "returnType" : "void",
    "comment" : "",
    "links" : [ ]
  } ],
  "variableNames" : [ "mLayoutParams", "mOutFrame", "mOutContentInsets", "mOutStableInsets", "mOutDisplayCutout", "mOutInsetsState", "mOutControls" ],
  "methodNames" : [ " void runBenchmark(ManualBenchmarkState state) throws RemoteException" ]
}