{
  "filePath" : "/home/maryam/clearblue/files/android-source-35/android/view/DisplayAddress.java",
  "packageName" : "android.view",
  "className" : "Network",
  "comment" : "\n     * Address for a network-connected display.\n     ",
  "links" : [ ],
  "variables" : [ {
    "name" : "mMacAddress",
    "type" : "String",
    "comment" : "",
    "links" : [ ]
  }, {
    "name" : "CREATOR",
    "type" : "Parcelable.Creator<Network>",
    "comment" : "",
    "links" : [ ]
  } ],
  "methods" : [ {
    "name" : "public boolean equals(@Nullable Object other)",
    "returnType" : "boolean",
    "comment" : "",
    "links" : [ ]
  }, {
    "name" : "public String toString()",
    "returnType" : "String",
    "comment" : "",
    "links" : [ ]
  }, {
    "name" : "public int hashCode()",
    "returnType" : "int",
    "comment" : "",
    "links" : [ ]
  }, {
    "name" : "public void writeToParcel(Parcel out, int flags)",
    "returnType" : "void",
    "comment" : "",
    "links" : [ ]
  } ],
  "methodNames" : [ "public boolean equals(@Nullable Object other)", "public String toString()", "public int hashCode()", "public void writeToParcel(Parcel out, int flags)" ],
  "variableNames" : [ "mMacAddress", "CREATOR" ]
}