{
  "filePath" : "/home/maryam/clearblue/files/android-source-35/android/icu/util/StringTrieBuilder.java",
  "packageName" : "android.icu.util",
  "className" : "ListBranchNode",
  "comment" : "",
  "links" : [ ],
  "variables" : [ {
    "name" : "equal",
    "type" : "Node[]",
    "comment" : " null means \"has final value\".",
    "links" : [ ]
  }, {
    "name" : "length",
    "type" : "int",
    "comment" : "",
    "links" : [ ]
  }, {
    "name" : "values",
    "type" : "int[]",
    "comment" : "",
    "links" : [ ]
  }, {
    "name" : "units",
    "type" : "char[]",
    "comment" : "",
    "links" : [ ]
  } ],
  "methods" : [ {
    "name" : "public boolean equals(Object other)",
    "returnType" : "boolean",
    "comment" : "",
    "links" : [ ]
  }, {
    "name" : "public int hashCode()",
    "returnType" : "int",
    "comment" : "",
    "links" : [ ]
  }, {
    "name" : "public int markRightEdgesFirst(int edgeNumber)",
    "returnType" : "int",
    "comment" : "",
    "links" : [ ]
  }, {
    "name" : "public void write(StringTrieBuilder builder)",
    "returnType" : "void",
    "comment" : "",
    "links" : [ ]
  }, {
    "name" : "public void add(int c, int value)",
    "returnType" : "void",
    "comment" : " Adds a unit with a final value.",
    "links" : [ ]
  }, {
    "name" : "public void add(int c, Node node)",
    "returnType" : "void",
    "comment" : " Adds a unit which leads to another match node.",
    "links" : [ ]
  } ],
  "methodNames" : [ "public boolean equals(Object other)", "public int hashCode()", "public int markRightEdgesFirst(int edgeNumber)", "public void write(StringTrieBuilder builder)", "public void add(int c, int value)", "public void add(int c, Node node)" ],
  "variableNames" : [ "equal", "length", "values", "units" ]
}