{
  "filePath" : "/home/maryam/clearblue/files/android-source-30/android/text/TextUtils.java",
  "packageName" : "android.text",
  "className" : "SimpleStringSplitter",
  "comment" : "\n     * A simple string splitter.\n     *\n     * <p>If the final character in the string to split is the delimiter then no empty string will\n     * be returned for the empty string after that delimeter. That is, splitting <tt>\"a,b,\"</tt> on\n     * comma will return <tt>\"a\", \"b\"</tt>, not <tt>\"a\", \"b\", \"\"</tt>.\n     ",
  "variables" : [ {
    "name" : "mString",
    "type" : "String",
    "comment" : "",
    "links" : [ ]
  }, {
    "name" : "mDelimiter",
    "type" : "char",
    "comment" : "",
    "links" : [ ]
  }, {
    "name" : "mPosition",
    "type" : "int",
    "comment" : "",
    "links" : [ ]
  }, {
    "name" : "mLength",
    "type" : "int",
    "comment" : "",
    "links" : [ ]
  } ],
  "methods" : [ {
    "name" : "public void setString(String string)",
    "returnType" : "void",
    "comment" : "\n         * Sets the string to split\n         * @param string the string to split\n         ",
    "links" : [ ]
  }, {
    "name" : "public Iterator<String> iterator()",
    "returnType" : "Iterator<String>",
    "comment" : "",
    "links" : [ ]
  }, {
    "name" : "public boolean hasNext()",
    "returnType" : "boolean",
    "comment" : "",
    "links" : [ ]
  }, {
    "name" : "public String next()",
    "returnType" : "String",
    "comment" : "",
    "links" : [ ]
  }, {
    "name" : "public void remove()",
    "returnType" : "void",
    "comment" : "",
    "links" : [ ]
  } ],
  "variableNames" : [ "mString", "mDelimiter", "mPosition", "mLength" ],
  "methodNames" : [ "public void setString(String string)", "public Iterator<String> iterator()", "public boolean hasNext()", "public String next()", "public void remove()" ]
}