{
  "filePath" : "/home/maryam/clearblue/files/android-source-35/android/net/wifi/nl80211/WifiNl80211Manager.java",
  "packageName" : "android.net.wifi.nl80211",
  "className" : "ScanEventHandler",
  "comment" : "",
  "links" : [ ],
  "variables" : [ {
    "name" : "mExecutor",
    "type" : "Executor",
    "comment" : "",
    "links" : [ ]
  }, {
    "name" : "mCallback",
    "type" : "ScanEventCallback",
    "comment" : "",
    "links" : [ ]
  } ],
  "methods" : [ {
    "name" : "public void OnScanResultReady()",
    "returnType" : "void",
    "comment" : "",
    "links" : [ ]
  }, {
    "name" : "public void OnScanFailed()",
    "returnType" : "void",
    "comment" : "",
    "links" : [ ]
  }, {
    "name" : "public void OnScanRequestFailed(int errorCode)",
    "returnType" : "void",
    "comment" : "",
    "links" : [ ]
  } ],
  "methodNames" : [ "public void OnScanResultReady()", "public void OnScanFailed()", "public void OnScanRequestFailed(int errorCode)" ],
  "variableNames" : [ "mExecutor", "mCallback" ]
}