{
  "filePath" : "/home/maryam/clearblue/files/android-source-35/android/view/inspector/IntFlagMapping.java",
  "packageName" : "android.view.inspector",
  "className" : "Flag",
  "comment" : "\n     * Inner class that holds the name, mask, and target value of a flag\n     ",
  "links" : [ ],
  "variables" : [ {
    "name" : "mName",
    "type" : "String",
    "comment" : "",
    "links" : [ ]
  }, {
    "name" : "mTarget",
    "type" : "int",
    "comment" : "",
    "links" : [ ]
  }, {
    "name" : "mMask",
    "type" : "int",
    "comment" : "",
    "links" : [ ]
  } ],
  "methods" : [ {
    "name" : "private boolean isEnabledFor(int value)",
    "returnType" : "boolean",
    "comment" : "\n         * Compare the supplied property value against the mask and target.\n         *\n         * @param value The value to check\n         * @return True if this flag is enabled\n         ",
    "links" : [ ]
  } ],
  "methodNames" : [ "private boolean isEnabledFor(int value)" ],
  "variableNames" : [ "mName", "mTarget", "mMask" ]
}