{
  "filePath" : "/home/maryam/clearblue/files/android-source-35/android/text/Hyphenator.java",
  "packageName" : "android.text",
  "className" : "Hyphenator",
  "comment" : "\n * Does the native Hyphenator initialization.\n *\n * @hide\n ",
  "links" : [ ],
  "variables" : [ ],
  "methods" : [ {
    "name" : "public static void init()",
    "returnType" : "void",
    "comment" : " This method is called from Zygote.",
    "links" : [ ]
  }, {
    "name" : "private static native void nInit()",
    "returnType" : "void",
    "comment" : "",
    "links" : [ ]
  } ],
  "methodNames" : [ "public static void init()", "private static native void nInit()" ],
  "variableNames" : [ ]
}