{
  "filePath" : "/home/maryam/clearblue/files/android-source-35/android/content/pm/ProcessInfo.java",
  "packageName" : "android.content.pm",
  "className" : "ProcessInfo",
  "comment" : "\n * Information about a process an app may run.  This corresponds to information collected from the\n * AndroidManifest.xml's &lt;permission-group&gt; tags.\n * @hide\n ",
  "links" : [ ],
  "variables" : [ {
    "name" : "name",
    "type" : "String",
    "comment" : "\n     * The name of the process, fully-qualified based on the app's package name.\n     ",
    "links" : [ ]
  }, {
    "name" : "deniedPermissions",
    "type" : "ArraySet<String>",
    "comment" : "\n     * If non-null, these are permissions that are not allowed in this process.\n     ",
    "links" : [ ]
  }, {
    "name" : "gwpAsanMode",
    "type" : "int",
    "comment" : "\n     * Indicates if the process has requested GWP-ASan to be enabled, disabled, or left unspecified.\n     ",
    "links" : [ ]
  }, {
    "name" : "memtagMode",
    "type" : "int",
    "comment" : "\n     * Indicates if the process has requested Memtag to be enabled (in sync or async mode),\n     * disabled, or left unspecified.\n     ",
    "links" : [ ]
  }, {
    "name" : "nativeHeapZeroInitialized",
    "type" : "int",
    "comment" : "\n     * Enable automatic zero-initialization of native heap memory allocations.\n     ",
    "links" : [ ]
  }, {
    "name" : "useEmbeddedDex",
    "type" : "boolean",
    "comment" : "\n     * Enable use of embedded dex in the APK, rather than extracted or locally compiled variants.\n     * If false (default), the parent app's configuration determines behavior.\n     ",
    "links" : [ ]
  }, {
    "name" : "sParcellingForDeniedPermissions",
    "type" : "Parcelling<ArraySet<String>>",
    "comment" : "",
    "links" : [ ]
  }, {
    "name" : "CREATOR",
    "type" : "Parcelable.Creator<ProcessInfo>",
    "comment" : "",
    "links" : [ ]
  } ],
  "methods" : [ {
    "name" : "public void writeToParcel(@NonNull Parcel dest, int flags)",
    "returnType" : "void",
    "comment" : "",
    "links" : [ ]
  }, {
    "name" : "public int describeContents()",
    "returnType" : "int",
    "comment" : "",
    "links" : [ ]
  }, {
    "name" : "private void __metadata()",
    "returnType" : "void",
    "comment" : "",
    "links" : [ ]
  } ],
  "methodNames" : [ "public void writeToParcel(@NonNull Parcel dest, int flags)", "public int describeContents()", "private void __metadata()" ],
  "variableNames" : [ "name", "deniedPermissions", "gwpAsanMode", "memtagMode", "nativeHeapZeroInitialized", "useEmbeddedDex", "sParcellingForDeniedPermissions", "CREATOR" ]
}