{
  "filePath" : "/home/maryam/clearblue/files/android-source-35/android/health/connect/accesslog/AccessLog.java",
  "packageName" : "android.health.connect.accesslog",
  "className" : "OperationType",
  "comment" : " Identifier for Operation type. ",
  "links" : [ ],
  "variables" : [ {
    "name" : "OPERATION_TYPE_READ",
    "type" : "int",
    "comment" : " Identifier for read operation done on user health data. ",
    "links" : [ ]
  }, {
    "name" : "OPERATION_TYPE_UPSERT",
    "type" : "int",
    "comment" : " Identifier for update or insert operation done on user health data. ",
    "links" : [ ]
  }, {
    "name" : "OPERATION_TYPE_DELETE",
    "type" : "int",
    "comment" : " Identifier for delete operation done on user health data. ",
    "links" : [ ]
  } ],
  "methods" : [ ],
  "methodNames" : [ ],
  "variableNames" : [ "OPERATION_TYPE_READ", "OPERATION_TYPE_UPSERT", "OPERATION_TYPE_DELETE" ]
}