{
  "filePath" : "/home/maryam/clearblue/files/android-source-35/android/adservices/signals/UpdateSignalsInput.java",
  "packageName" : "android.adservices.signals",
  "className" : "UpdateSignalsInput",
  "comment" : "\n * The input object wrapping the parameters for the updateSignals API.\n *\n * <p>Refer to {@link UpdateSignalsRequest} for more information about the parameters.\n *\n * @hide\n ",
  "links" : [ "android.adservices.signals.UpdateSignalsRequest" ],
  "variables" : [ {
    "name" : "mUpdateUri",
    "type" : "Uri",
    "comment" : "",
    "links" : [ ]
  }, {
    "name" : "mCallerPackageName",
    "type" : "String",
    "comment" : "",
    "links" : [ ]
  }, {
    "name" : "CREATOR",
    "type" : "Creator<UpdateSignalsInput>",
    "comment" : "",
    "links" : [ ]
  } ],
  "methods" : [ {
    "name" : "public Uri getUpdateUri()",
    "returnType" : "Uri",
    "comment" : "\n     * @return the {@link Uri} from which the signal updates will be fetched.\n     ",
    "links" : [ "android.net.Uri" ]
  }, {
    "name" : "public String getCallerPackageName()",
    "returnType" : "String",
    "comment" : "\n     * @return the caller app's package name.\n     ",
    "links" : [ ]
  }, {
    "name" : "public int describeContents()",
    "returnType" : "int",
    "comment" : "",
    "links" : [ ]
  }, {
    "name" : "public void writeToParcel(@NonNull Parcel dest, int flags)",
    "returnType" : "void",
    "comment" : "",
    "links" : [ ]
  }, {
    "name" : "public boolean equals(Object o)",
    "returnType" : "boolean",
    "comment" : "\n     * @return {@code true} if and only if the other object is {@link UpdateSignalsRequest} with the\n     *     same update URI and package name\n     ",
    "links" : [ "android.adservices.signals.UpdateSignalsRequest" ]
  }, {
    "name" : "public int hashCode()",
    "returnType" : "int",
    "comment" : "\n     * @return the hash of the {@link UpdateSignalsInput} object's data.\n     ",
    "links" : [ "android.adservices.signals.UpdateSignalsInput" ]
  }, {
    "name" : "public String toString()",
    "returnType" : "String",
    "comment" : "",
    "links" : [ ]
  } ],
  "methodNames" : [ "public Uri getUpdateUri()", "public String getCallerPackageName()", "public int describeContents()", "public void writeToParcel(@NonNull Parcel dest, int flags)", "public boolean equals(Object o)", "public int hashCode()", "public String toString()" ],
  "variableNames" : [ "mUpdateUri", "mCallerPackageName", "CREATOR" ]
}