{
  "filePath" : "/home/maryam/clearblue/files/android-source-35/android/adservices/topics/EncryptedTopic.java",
  "packageName" : "android.adservices.topics",
  "className" : "EncryptedTopic",
  "comment" : "\n * Encrypted form of {@link android.adservices.topics.Topic}. This object will be used to return\n * encrypted topic cipher text along with necessary fields required to decrypt it.\n *\n * <p>Decryption of {@link EncryptedTopic#getEncryptedTopic()} should give json string for {@link\n * Topic}. Example of decrypted json string: {@code { \"taxonomy_version\": 5, \"model_version\": 2,\n * \"topic_id\": 10010 }}\n *\n * <p>Decryption of cipher text is expected to happen on the server with the corresponding algorithm\n * and private key for the public key {@link EncryptedTopic#getKeyIdentifier()}}.\n *\n * <p>Detailed steps on decryption can be found on <a\n * href=\"https://developer.android.com/design-for-safety/privacy-sandbox/guides/topics\">Developer\n * Guide</a>.\n ",
  "links" : [ "android.adservices.topics.EncryptedTopic#getEncryptedTopic()", "android.adservices.topics.EncryptedTopic#getKeyIdentifier()", "android.adservices.topics.Topic" ],
  "variables" : [ {
    "name" : "mEncryptedTopic",
    "type" : "byte[]",
    "comment" : "",
    "links" : [ ]
  }, {
    "name" : "mKeyIdentifier",
    "type" : "String",
    "comment" : "",
    "links" : [ ]
  }, {
    "name" : "mEncapsulatedKey",
    "type" : "byte[]",
    "comment" : "",
    "links" : [ ]
  } ],
  "methods" : [ {
    "name" : "public byte[] getEncryptedTopic()",
    "returnType" : "byte[]",
    "comment" : " Returns encrypted bytes for the JSON version of the {@link Topic} object as cipher text. ",
    "links" : [ "android.adservices.topics.Topic" ]
  }, {
    "name" : "public String getKeyIdentifier()",
    "returnType" : "String",
    "comment" : " Returns key identifier for the used encryption key. ",
    "links" : [ ]
  }, {
    "name" : "public byte[] getEncapsulatedKey()",
    "returnType" : "byte[]",
    "comment" : " Returns the encapsulated key generated during HPKE setup. ",
    "links" : [ ]
  }, {
    "name" : "public boolean equals(Object object)",
    "returnType" : "boolean",
    "comment" : "",
    "links" : [ ]
  }, {
    "name" : "public int hashCode()",
    "returnType" : "int",
    "comment" : "",
    "links" : [ ]
  }, {
    "name" : "public java.lang.String toString()",
    "returnType" : "java.lang.String",
    "comment" : "",
    "links" : [ ]
  } ],
  "methodNames" : [ "public byte[] getEncryptedTopic()", "public String getKeyIdentifier()", "public byte[] getEncapsulatedKey()", "public boolean equals(Object object)", "public int hashCode()", "public java.lang.String toString()" ],
  "variableNames" : [ "mEncryptedTopic", "mKeyIdentifier", "mEncapsulatedKey" ]
}