{
  "filePath" : "/home/maryam/clearblue/files/android-source-30/android/view/View_Delegate.java",
  "packageName" : "android.view",
  "className" : "View_Delegate",
  "comment" : "\n * Delegate used to provide new implementation of a select few methods of {@link View}\n *\n * Through the layoutlib_create tool, the original  methods of View have been replaced\n * by calls to methods of the same name in this delegate class.\n *\n ",
  "variables" : [ ],
  "methods" : [ {
    "name" : " static boolean isInEditMode(View thisView)",
    "returnType" : "boolean",
    "comment" : "",
    "links" : [ ]
  }, {
    "name" : " static IBinder getWindowToken(View thisView)",
    "returnType" : "IBinder",
    "comment" : "",
    "links" : [ ]
  }, {
    "name" : " static void draw(View thisView, Canvas canvas)",
    "returnType" : "void",
    "comment" : "",
    "links" : [ ]
  }, {
    "name" : " static boolean draw(View thisView, Canvas canvas, ViewGroup parent, long drawingTime)",
    "returnType" : "boolean",
    "comment" : "",
    "links" : [ ]
  }, {
    "name" : " static void measure(View thisView, int widthMeasureSpec, int heightMeasureSpec)",
    "returnType" : "void",
    "comment" : "",
    "links" : [ ]
  }, {
    "name" : " static void layout(View thisView, int l, int t, int r, int b)",
    "returnType" : "void",
    "comment" : "",
    "links" : [ ]
  }, {
    "name" : " static void dispatchDetachedFromWindow(View thisView)",
    "returnType" : "void",
    "comment" : "",
    "links" : [ ]
  } ],
  "variableNames" : [ ],
  "methodNames" : [ " static boolean isInEditMode(View thisView)", " static IBinder getWindowToken(View thisView)", " static void draw(View thisView, Canvas canvas)", " static boolean draw(View thisView, Canvas canvas, ViewGroup parent, long drawingTime)", " static void measure(View thisView, int widthMeasureSpec, int heightMeasureSpec)", " static void layout(View thisView, int l, int t, int r, int b)", " static void dispatchDetachedFromWindow(View thisView)" ]
}