{
  "filePath" : "/home/maryam/clearblue/files/android-source-35/android/telephony/CellIdentityWcdma.java",
  "packageName" : "android.telephony",
  "className" : "CellIdentityWcdma",
  "comment" : "\n * CellIdentity to represent a unique UMTS cell\n ",
  "links" : [ ],
  "variables" : [ {
    "name" : "TAG",
    "type" : "String",
    "comment" : "",
    "links" : [ ]
  }, {
    "name" : "DBG",
    "type" : "boolean",
    "comment" : "",
    "links" : [ ]
  }, {
    "name" : "MAX_LAC",
    "type" : "int",
    "comment" : "",
    "links" : [ ]
  }, {
    "name" : "MAX_CID",
    "type" : "int",
    "comment" : "",
    "links" : [ ]
  }, {
    "name" : "MAX_PSC",
    "type" : "int",
    "comment" : "",
    "links" : [ ]
  }, {
    "name" : "MAX_UARFCN",
    "type" : "int",
    "comment" : " a 14 bit number; TS 25.331 ex sec 10.3.8.15",
    "links" : [ ]
  }, {
    "name" : "mLac",
    "type" : "int",
    "comment" : " 16-bit Location Area Code, 0..65535",
    "links" : [ ]
  }, {
    "name" : "mCid",
    "type" : "int",
    "comment" : " 28-bit UMTS Cell Identity described in TS 25.331, 0..268435455",
    "links" : [ ]
  }, {
    "name" : "mPsc",
    "type" : "int",
    "comment" : " 9-bit UMTS Primary Scrambling Code described in TS 25.331, 0..511",
    "links" : [ ]
  }, {
    "name" : "mUarfcn",
    "type" : "int",
    "comment" : " 16-bit UMTS Absolute RF Channel Number described in TS 25.101 sec. 5.4.4",
    "links" : [ ]
  }, {
    "name" : "mAdditionalPlmns",
    "type" : "ArraySet<String>",
    "comment" : " a list of additional PLMN-IDs reported for this cell",
    "links" : [ ]
  }, {
    "name" : "mCsgInfo",
    "type" : "ClosedSubscriberGroupInfo",
    "comment" : "",
    "links" : [ ]
  }, {
    "name" : "CREATOR",
    "type" : "Creator<CellIdentityWcdma>",
    "comment" : " Implement the Parcelable interface ",
    "links" : [ ]
  } ],
  "methods" : [ {
    "name" : "public CellIdentityWcdma sanitizeLocationInfo()",
    "returnType" : "CellIdentityWcdma",
    "comment" : " @hide ",
    "links" : [ ]
  }, {
    "name" : " CellIdentityWcdma copy()",
    "returnType" : "CellIdentityWcdma",
    "comment" : "",
    "links" : [ ]
  }, {
    "name" : "protected void updateGlobalCellId()",
    "returnType" : "void",
    "comment" : " @hide ",
    "links" : [ ]
  }, {
    "name" : "public int getMcc()",
    "returnType" : "int",
    "comment" : "\n     * @return 3-digit Mobile Country Code, 0..999,\n     *         {@link android.telephony.CellInfo#UNAVAILABLE UNAVAILABLE} if unavailable.\n     * @deprecated Use {@link #getMccString} instead.\n     ",
    "links" : [ "#getMccString", "android.telephony.CellInfo#UNAVAILABLE" ]
  }, {
    "name" : "public int getMnc()",
    "returnType" : "int",
    "comment" : "\n     * @return 2 or 3-digit Mobile Network Code, 0..999,\n     *         {@link android.telephony.CellInfo#UNAVAILABLE UNAVAILABLE} if unavailable.\n     * @deprecated Use {@link #getMncString} instead.\n     ",
    "links" : [ "android.telephony.CellInfo#UNAVAILABLE", "#getMncString" ]
  }, {
    "name" : "public int getLac()",
    "returnType" : "int",
    "comment" : "\n     * @return 16-bit Location Area Code, 0..65535,\n     *         {@link android.telephony.CellInfo#UNAVAILABLE UNAVAILABLE} if unavailable.\n     ",
    "links" : [ "android.telephony.CellInfo#UNAVAILABLE" ]
  }, {
    "name" : "public int getCid()",
    "returnType" : "int",
    "comment" : "\n     * @return CID\n     * 28-bit UMTS Cell Identity described in TS 25.331, 0..268435455,\n     *         {@link android.telephony.CellInfo#UNAVAILABLE UNAVAILABLE} if unavailable.\n     ",
    "links" : [ "android.telephony.CellInfo#UNAVAILABLE" ]
  }, {
    "name" : "public int getPsc()",
    "returnType" : "int",
    "comment" : "\n     * @return 9-bit UMTS Primary Scrambling Code described in TS 25.331, 0..511,\n     *         {@link android.telephony.CellInfo#UNAVAILABLE UNAVAILABLE} if unavailable.\n     ",
    "links" : [ "android.telephony.CellInfo#UNAVAILABLE" ]
  }, {
    "name" : "public String getMccString()",
    "returnType" : "String",
    "comment" : "\n     * @return Mobile Country Code in string version, null if unavailable.\n     ",
    "links" : [ ]
  }, {
    "name" : "public String getMncString()",
    "returnType" : "String",
    "comment" : "\n     * @return Mobile Network Code in string version, null if unavailable.\n     ",
    "links" : [ ]
  }, {
    "name" : "public String getMobileNetworkOperator()",
    "returnType" : "String",
    "comment" : "\n     * @return a 5 or 6 character string (MCC+MNC), null if any field is unknown\n     ",
    "links" : [ ]
  }, {
    "name" : "public int hashCode()",
    "returnType" : "int",
    "comment" : "",
    "links" : [ ]
  }, {
    "name" : "public int getUarfcn()",
    "returnType" : "int",
    "comment" : "\n     * @return 16-bit UMTS Absolute RF Channel Number,\n     *         {@link android.telephony.CellInfo#UNAVAILABLE UNAVAILABLE} if unavailable.\n     ",
    "links" : [ "android.telephony.CellInfo#UNAVAILABLE" ]
  }, {
    "name" : "public int getChannelNumber()",
    "returnType" : "int",
    "comment" : " @hide ",
    "links" : [ ]
  }, {
    "name" : "public Set<String> getAdditionalPlmns()",
    "returnType" : "Set<String>",
    "comment" : "\n     * @return a list of additional PLMN IDs supported by this cell.\n     ",
    "links" : [ ]
  }, {
    "name" : "public ClosedSubscriberGroupInfo getClosedSubscriberGroupInfo()",
    "returnType" : "ClosedSubscriberGroupInfo",
    "comment" : "\n     * @return closed subscriber group information about the cell if available, otherwise null.\n     ",
    "links" : [ ]
  }, {
    "name" : "public GsmCellLocation asCellLocation()",
    "returnType" : "GsmCellLocation",
    "comment" : " @hide ",
    "links" : [ ]
  }, {
    "name" : "public boolean equals(Object other)",
    "returnType" : "boolean",
    "comment" : "",
    "links" : [ ]
  }, {
    "name" : "public String toString()",
    "returnType" : "String",
    "comment" : "",
    "links" : [ ]
  }, {
    "name" : "public void writeToParcel(Parcel dest, int flags)",
    "returnType" : "void",
    "comment" : " Implement the Parcelable interface ",
    "links" : [ ]
  }, {
    "name" : "protected static CellIdentityWcdma createFromParcelBody(Parcel in)",
    "returnType" : "CellIdentityWcdma",
    "comment" : " @hide ",
    "links" : [ ]
  } ],
  "methodNames" : [ "public CellIdentityWcdma sanitizeLocationInfo()", " CellIdentityWcdma copy()", "protected void updateGlobalCellId()", "public int getMcc()", "public int getMnc()", "public int getLac()", "public int getCid()", "public int getPsc()", "public String getMccString()", "public String getMncString()", "public String getMobileNetworkOperator()", "public int hashCode()", "public int getUarfcn()", "public int getChannelNumber()", "public Set<String> getAdditionalPlmns()", "public ClosedSubscriberGroupInfo getClosedSubscriberGroupInfo()", "public GsmCellLocation asCellLocation()", "public boolean equals(Object other)", "public String toString()", "public void writeToParcel(Parcel dest, int flags)", "protected static CellIdentityWcdma createFromParcelBody(Parcel in)" ],
  "variableNames" : [ "TAG", "DBG", "MAX_LAC", "MAX_CID", "MAX_PSC", "MAX_UARFCN", "mLac", "mCid", "mPsc", "mUarfcn", "mAdditionalPlmns", "mCsgInfo", "CREATOR" ]
}