{
  "filePath" : "/home/maryam/clearblue/files/android-source-35/android/icu/lang/UCharacter.java",
  "packageName" : "android.icu.lang",
  "className" : "GraphemeClusterBreak",
  "comment" : "\n     * Grapheme Cluster Break constants.\n     * @see UProperty#GRAPHEME_CLUSTER_BREAK\n     ",
  "links" : [ ],
  "variables" : [ {
    "name" : "OTHER",
    "type" : "int",
    "comment" : "\n         ",
    "links" : [ ]
  }, {
    "name" : "CONTROL",
    "type" : "int",
    "comment" : "\n         ",
    "links" : [ ]
  }, {
    "name" : "CR",
    "type" : "int",
    "comment" : "\n         ",
    "links" : [ ]
  }, {
    "name" : "EXTEND",
    "type" : "int",
    "comment" : "\n         ",
    "links" : [ ]
  }, {
    "name" : "L",
    "type" : "int",
    "comment" : "\n         ",
    "links" : [ ]
  }, {
    "name" : "LF",
    "type" : "int",
    "comment" : "\n         ",
    "links" : [ ]
  }, {
    "name" : "LV",
    "type" : "int",
    "comment" : "\n         ",
    "links" : [ ]
  }, {
    "name" : "LVT",
    "type" : "int",
    "comment" : "\n         ",
    "links" : [ ]
  }, {
    "name" : "T",
    "type" : "int",
    "comment" : "\n         ",
    "links" : [ ]
  }, {
    "name" : "V",
    "type" : "int",
    "comment" : "\n         ",
    "links" : [ ]
  }, {
    "name" : "SPACING_MARK",
    "type" : "int",
    "comment" : "\n         ",
    "links" : [ ]
  }, {
    "name" : "PREPEND",
    "type" : "int",
    "comment" : "\n         ",
    "links" : [ ]
  }, {
    "name" : "REGIONAL_INDICATOR",
    "type" : "int",
    "comment" : "",
    "links" : [ ]
  }, {
    "name" : "E_BASE",
    "type" : "int",
    "comment" : "",
    "links" : [ ]
  }, {
    "name" : "E_BASE_GAZ",
    "type" : "int",
    "comment" : "",
    "links" : [ ]
  }, {
    "name" : "E_MODIFIER",
    "type" : "int",
    "comment" : "",
    "links" : [ ]
  }, {
    "name" : "GLUE_AFTER_ZWJ",
    "type" : "int",
    "comment" : "",
    "links" : [ ]
  }, {
    "name" : "ZWJ",
    "type" : "int",
    "comment" : "",
    "links" : [ ]
  }, {
    "name" : "COUNT",
    "type" : "int",
    "comment" : "\n         * One more than the highest normal GraphemeClusterBreak value.\n         * The highest value is available via UCharacter.getIntPropertyMaxValue(UProperty.GRAPHEME_CLUSTER_BREAK).\n         *\n         * @deprecated ICU 58 The numeric value may change over time, see ICU ticket #12420.\n         * @hide unsupported on Android\n         ",
    "links" : [ ]
  } ],
  "methods" : [ ],
  "methodNames" : [ ],
  "variableNames" : [ "OTHER", "CONTROL", "CR", "EXTEND", "L", "LF", "LV", "LVT", "T", "V", "SPACING_MARK", "PREPEND", "REGIONAL_INDICATOR", "E_BASE", "E_BASE_GAZ", "E_MODIFIER", "GLUE_AFTER_ZWJ", "ZWJ", "COUNT" ]
}