{
  "filePath" : "/home/maryam/clearblue/files/android-source-30/android/media/AsyncPlayer.java",
  "packageName" : "android.media",
  "className" : "Command",
  "comment" : "",
  "variables" : [ {
    "name" : "code",
    "type" : "int",
    "comment" : "",
    "links" : [ ]
  }, {
    "name" : "context",
    "type" : "Context",
    "comment" : "",
    "links" : [ ]
  }, {
    "name" : "uri",
    "type" : "Uri",
    "comment" : "",
    "links" : [ ]
  }, {
    "name" : "looping",
    "type" : "boolean",
    "comment" : "",
    "links" : [ ]
  }, {
    "name" : "attributes",
    "type" : "AudioAttributes",
    "comment" : "",
    "links" : [ ]
  }, {
    "name" : "requestTime",
    "type" : "long",
    "comment" : "",
    "links" : [ ]
  } ],
  "methods" : [ {
    "name" : "public String toString()",
    "returnType" : "String",
    "comment" : "",
    "links" : [ ]
  } ],
  "variableNames" : [ "code", "context", "uri", "looping", "attributes", "requestTime" ],
  "methodNames" : [ "public String toString()" ]
}