{
  "filePath" : "/home/maryam/clearblue/files/android-source-35/android/net/wifi/p2p/WifiP2pGroup.java",
  "packageName" : "android.net.wifi.p2p",
  "className" : "P2pGroupClientEapolIpAddressData",
  "comment" : "\n     * P2P Client IPV4 address allocated via EAPOL-Key exchange.\n     * @hide\n     ",
  "links" : [ ],
  "variables" : [ {
    "name" : "mIpAddressClient",
    "type" : "Inet4Address",
    "comment" : "\n         * The P2P Client IP address.\n         ",
    "links" : [ ]
  }, {
    "name" : "mIpAddressGo",
    "type" : "Inet4Address",
    "comment" : "\n         * The P2P Group Owner IP address.\n         ",
    "links" : [ ]
  }, {
    "name" : "mIpAddressMask",
    "type" : "Inet4Address",
    "comment" : "\n         * The subnet that the P2P Group Owner is using.\n         ",
    "links" : [ ]
  } ],
  "methods" : [ ],
  "methodNames" : [ ],
  "variableNames" : [ "mIpAddressClient", "mIpAddressGo", "mIpAddressMask" ]
}