{
  "filePath" : "/home/maryam/clearblue/files/android-source-35/android/view/AbsSavedState.java",
  "packageName" : "android.view",
  "className" : "AbsSavedState",
  "comment" : "\n * A {@link Parcelable} implementation that should be used by inheritance\n * hierarchies to ensure the state of all classes along the chain is saved.\n ",
  "links" : [ "android.os.Parcelable" ],
  "variables" : [ {
    "name" : "EMPTY_STATE",
    "type" : "AbsSavedState",
    "comment" : "",
    "links" : [ ]
  }, {
    "name" : "mSuperState",
    "type" : "Parcelable",
    "comment" : "",
    "links" : [ ]
  }, {
    "name" : "CREATOR",
    "type" : "Parcelable.Creator<AbsSavedState>",
    "comment" : "",
    "links" : [ ]
  } ],
  "methods" : [ {
    "name" : "public final Parcelable getSuperState()",
    "returnType" : "Parcelable",
    "comment" : "",
    "links" : [ ]
  }, {
    "name" : "public int describeContents()",
    "returnType" : "int",
    "comment" : "",
    "links" : [ ]
  }, {
    "name" : "public void writeToParcel(Parcel dest, int flags)",
    "returnType" : "void",
    "comment" : "",
    "links" : [ ]
  } ],
  "methodNames" : [ "public final Parcelable getSuperState()", "public int describeContents()", "public void writeToParcel(Parcel dest, int flags)" ],
  "variableNames" : [ "EMPTY_STATE", "mSuperState", "CREATOR" ]
}