{
  "filePath" : "/home/maryam/clearblue/files/android-source-30/android/widget/DateTimeView.java",
  "packageName" : "android.widget",
  "className" : "ReceiverInfo",
  "comment" : "",
  "variables" : [ {
    "name" : "mAttachedViews",
    "type" : "ArrayList<DateTimeView>",
    "comment" : "",
    "links" : [ ]
  }, {
    "name" : "mReceiver",
    "type" : "BroadcastReceiver",
    "comment" : "",
    "links" : [ ]
  }, {
    "name" : "mObserver",
    "type" : "ContentObserver",
    "comment" : "",
    "links" : [ ]
  }, {
    "name" : "mHandler",
    "type" : "Handler",
    "comment" : "",
    "links" : [ ]
  } ],
  "methods" : [ {
    "name" : "public void addView(DateTimeView v)",
    "returnType" : "void",
    "comment" : "",
    "links" : [ ]
  }, {
    "name" : "public void removeView(DateTimeView v)",
    "returnType" : "void",
    "comment" : "",
    "links" : [ ]
  }, {
    "name" : " void updateAll()",
    "returnType" : "void",
    "comment" : "",
    "links" : [ ]
  }, {
    "name" : " long getSoonestUpdateTime()",
    "returnType" : "long",
    "comment" : "",
    "links" : [ ]
  }, {
    "name" : " static final Context getApplicationContextIfAvailable(Context context)",
    "returnType" : "Context",
    "comment" : "",
    "links" : [ ]
  }, {
    "name" : " void register(Context context)",
    "returnType" : "void",
    "comment" : "",
    "links" : [ ]
  }, {
    "name" : " void unregister(Context context)",
    "returnType" : "void",
    "comment" : "",
    "links" : [ ]
  }, {
    "name" : "public void setHandler(Handler handler)",
    "returnType" : "void",
    "comment" : "",
    "links" : [ ]
  } ],
  "variableNames" : [ "mAttachedViews", "mReceiver", "mObserver", "mHandler" ],
  "methodNames" : [ "public void addView(DateTimeView v)", "public void removeView(DateTimeView v)", " void updateAll()", " long getSoonestUpdateTime()", " static final Context getApplicationContextIfAvailable(Context context)", " void register(Context context)", " void unregister(Context context)", "public void setHandler(Handler handler)" ]
}