{
  "filePath" : "/home/maryam/clearblue/files/android-source-35/android/media/RemoteControlClient.java",
  "packageName" : "android.media",
  "className" : "OnGetPlaybackPositionListener",
  "comment" : "\n     * Interface definition for a callback to be invoked when the media playback position is\n     * queried.\n     * @see RemoteControlClient#FLAG_KEY_MEDIA_POSITION_UPDATE\n     ",
  "links" : [ ],
  "variables" : [ ],
  "methods" : [ {
    "name" : " long onGetPlaybackPosition()",
    "returnType" : "long",
    "comment" : "\n         * Called on the implementer of the interface to query the current playback position.\n         * @return a negative value if the current playback position (or the last valid playback\n         *     position) is not known, or a zero or positive value expressed in ms indicating the\n         *     current position, or the last valid known position.\n         ",
    "links" : [ ]
  } ],
  "methodNames" : [ " long onGetPlaybackPosition()" ],
  "variableNames" : [ ]
}