{
  "filePath" : "/home/maryam/clearblue/files/android-source-35/android/media/permission/ClearCallingIdentityContext.java",
  "packageName" : "android.media.permission",
  "className" : "ClearCallingIdentityContext",
  "comment" : "\n * An RAII-style object, used to establish a scope in which the binder calling identity is cleared.\n *\n * <p>\n * Intended usage:\n * <pre>\n * void caller() {\n *   try (SafeCloseable ignored = ClearCallingIdentityContext.create()) {\n *       // Within this scope the binder calling identity is cleared.\n *       ...\n *   }\n *   // Outside the scope the calling identity is restored to its prior state.\n * </pre>\n *\n * @hide\n ",
  "links" : [ ],
  "variables" : [ {
    "name" : "mRestoreKey",
    "type" : "long",
    "comment" : "",
    "links" : [ ]
  } ],
  "methods" : [ {
    "name" : "public static SafeCloseable create()",
    "returnType" : "SafeCloseable",
    "comment" : "\n     * Creates a new instance.\n     * @return A {@link SafeCloseable}, intended to be used in a try-with-resource block.\n     ",
    "links" : [ "android.media.permission.SafeCloseable" ]
  }, {
    "name" : "public void close()",
    "returnType" : "void",
    "comment" : "",
    "links" : [ ]
  } ],
  "methodNames" : [ "public static SafeCloseable create()", "public void close()" ],
  "variableNames" : [ "mRestoreKey" ]
}