{
  "filePath" : "/home/maryam/clearblue/files/android-source-35/android/widget/CalendarView.java",
  "packageName" : "android.widget",
  "className" : "AbstractCalendarViewDelegate",
  "comment" : "\n     * An abstract class which can be used as a start for CalendarView implementations\n     ",
  "links" : [ ],
  "variables" : [ {
    "name" : "DEFAULT_MIN_DATE",
    "type" : "String",
    "comment" : " The default minimal date. ",
    "links" : [ ]
  }, {
    "name" : "DEFAULT_MAX_DATE",
    "type" : "String",
    "comment" : " The default maximal date. ",
    "links" : [ ]
  }, {
    "name" : "mDelegator",
    "type" : "CalendarView",
    "comment" : "",
    "links" : [ ]
  }, {
    "name" : "mContext",
    "type" : "Context",
    "comment" : "",
    "links" : [ ]
  }, {
    "name" : "mCurrentLocale",
    "type" : "Locale",
    "comment" : "",
    "links" : [ ]
  } ],
  "methods" : [ {
    "name" : "protected void setCurrentLocale(Locale locale)",
    "returnType" : "void",
    "comment" : "",
    "links" : [ ]
  }, {
    "name" : "public void setShownWeekCount(int count)",
    "returnType" : "void",
    "comment" : "",
    "links" : [ ]
  }, {
    "name" : "public int getShownWeekCount()",
    "returnType" : "int",
    "comment" : "",
    "links" : [ ]
  }, {
    "name" : "public void setSelectedWeekBackgroundColor(@ColorInt int color)",
    "returnType" : "void",
    "comment" : "",
    "links" : [ ]
  }, {
    "name" : "public int getSelectedWeekBackgroundColor()",
    "returnType" : "int",
    "comment" : "",
    "links" : [ ]
  }, {
    "name" : "public void setFocusedMonthDateColor(@ColorInt int color)",
    "returnType" : "void",
    "comment" : "",
    "links" : [ ]
  }, {
    "name" : "public int getFocusedMonthDateColor()",
    "returnType" : "int",
    "comment" : "",
    "links" : [ ]
  }, {
    "name" : "public void setUnfocusedMonthDateColor(@ColorInt int color)",
    "returnType" : "void",
    "comment" : "",
    "links" : [ ]
  }, {
    "name" : "public int getUnfocusedMonthDateColor()",
    "returnType" : "int",
    "comment" : "",
    "links" : [ ]
  }, {
    "name" : "public void setWeekNumberColor(@ColorInt int color)",
    "returnType" : "void",
    "comment" : "",
    "links" : [ ]
  }, {
    "name" : "public int getWeekNumberColor()",
    "returnType" : "int",
    "comment" : "",
    "links" : [ ]
  }, {
    "name" : "public void setWeekSeparatorLineColor(@ColorInt int color)",
    "returnType" : "void",
    "comment" : "",
    "links" : [ ]
  }, {
    "name" : "public int getWeekSeparatorLineColor()",
    "returnType" : "int",
    "comment" : "",
    "links" : [ ]
  }, {
    "name" : "public void setSelectedDateVerticalBar(@DrawableRes int resId)",
    "returnType" : "void",
    "comment" : "",
    "links" : [ ]
  }, {
    "name" : "public void setSelectedDateVerticalBar(Drawable drawable)",
    "returnType" : "void",
    "comment" : "",
    "links" : [ ]
  }, {
    "name" : "public Drawable getSelectedDateVerticalBar()",
    "returnType" : "Drawable",
    "comment" : "",
    "links" : [ ]
  }, {
    "name" : "public void setShowWeekNumber(boolean showWeekNumber)",
    "returnType" : "void",
    "comment" : "",
    "links" : [ ]
  }, {
    "name" : "public boolean getShowWeekNumber()",
    "returnType" : "boolean",
    "comment" : "",
    "links" : [ ]
  }, {
    "name" : "public void onConfigurationChanged(Configuration newConfig)",
    "returnType" : "void",
    "comment" : "",
    "links" : [ ]
  } ],
  "methodNames" : [ "protected void setCurrentLocale(Locale locale)", "public void setShownWeekCount(int count)", "public int getShownWeekCount()", "public void setSelectedWeekBackgroundColor(@ColorInt int color)", "public int getSelectedWeekBackgroundColor()", "public void setFocusedMonthDateColor(@ColorInt int color)", "public int getFocusedMonthDateColor()", "public void setUnfocusedMonthDateColor(@ColorInt int color)", "public int getUnfocusedMonthDateColor()", "public void setWeekNumberColor(@ColorInt int color)", "public int getWeekNumberColor()", "public void setWeekSeparatorLineColor(@ColorInt int color)", "public int getWeekSeparatorLineColor()", "public void setSelectedDateVerticalBar(@DrawableRes int resId)", "public void setSelectedDateVerticalBar(Drawable drawable)", "public Drawable getSelectedDateVerticalBar()", "public void setShowWeekNumber(boolean showWeekNumber)", "public boolean getShowWeekNumber()", "public void onConfigurationChanged(Configuration newConfig)" ],
  "variableNames" : [ "DEFAULT_MIN_DATE", "DEFAULT_MAX_DATE", "mDelegator", "mContext", "mCurrentLocale" ]
}