{
  "filePath" : "/home/maryam/clearblue/files/android-source-30/android/view/LayoutInflater.java",
  "packageName" : "android.view",
  "className" : "FactoryMerger",
  "comment" : "",
  "variables" : [ {
    "name" : "mF1",
    "type" : "Factory",
    "comment" : "",
    "links" : [ ]
  }, {
    "name" : "mF2",
    "type" : "Factory",
    "comment" : "",
    "links" : [ ]
  }, {
    "name" : "mF12",
    "type" : "Factory2",
    "comment" : "",
    "links" : [ ]
  }, {
    "name" : "mF22",
    "type" : "Factory2",
    "comment" : "",
    "links" : [ ]
  } ],
  "methods" : [ {
    "name" : "public View onCreateView(@NonNull String name, @NonNull Context context, @NonNull AttributeSet attrs)",
    "returnType" : "View",
    "comment" : "",
    "links" : [ ]
  }, {
    "name" : "public View onCreateView(@Nullable View parent, @NonNull String name, @NonNull Context context, @NonNull AttributeSet attrs)",
    "returnType" : "View",
    "comment" : "",
    "links" : [ ]
  } ],
  "variableNames" : [ "mF1", "mF2", "mF12", "mF22" ],
  "methodNames" : [ "public View onCreateView(@NonNull String name, @NonNull Context context, @NonNull AttributeSet attrs)", "public View onCreateView(@Nullable View parent, @NonNull String name, @NonNull Context context, @NonNull AttributeSet attrs)" ]
}