{
  "filePath" : "/home/maryam/clearblue/files/android-source-30/android/view/Surface.java",
  "packageName" : "android.view",
  "className" : "HwuiContext",
  "comment" : "",
  "variables" : [ {
    "name" : "mRenderNode",
    "type" : "RenderNode",
    "comment" : "",
    "links" : [ ]
  }, {
    "name" : "mHardwareRenderer",
    "type" : "HardwareRenderer",
    "comment" : "",
    "links" : [ ]
  }, {
    "name" : "mCanvas",
    "type" : "RecordingCanvas",
    "comment" : "",
    "links" : [ ]
  }, {
    "name" : "mIsWideColorGamut",
    "type" : "boolean",
    "comment" : "",
    "links" : [ ]
  } ],
  "methods" : [ {
    "name" : " Canvas lockCanvas(int width, int height)",
    "returnType" : "Canvas",
    "comment" : "",
    "links" : [ ]
  }, {
    "name" : " void unlockAndPost(Canvas canvas)",
    "returnType" : "void",
    "comment" : "",
    "links" : [ ]
  }, {
    "name" : " void updateSurface()",
    "returnType" : "void",
    "comment" : "",
    "links" : [ ]
  }, {
    "name" : " void destroy()",
    "returnType" : "void",
    "comment" : "",
    "links" : [ ]
  }, {
    "name" : " boolean isWideColorGamut()",
    "returnType" : "boolean",
    "comment" : "",
    "links" : [ ]
  } ],
  "variableNames" : [ "mRenderNode", "mHardwareRenderer", "mCanvas", "mIsWideColorGamut" ],
  "methodNames" : [ " Canvas lockCanvas(int width, int height)", " void unlockAndPost(Canvas canvas)", " void updateSurface()", " void destroy()", " boolean isWideColorGamut()" ]
}