{
  "filePath" : "/home/maryam/clearblue/files/android-source-35/android/app/smartspace/uitemplatedata/SubListTemplateData.java",
  "packageName" : "android.app.smartspace.uitemplatedata",
  "className" : "Builder",
  "comment" : "\n     * A builder for {@link SubListTemplateData} object.\n     *\n     * @hide\n     ",
  "links" : [ "android.app.smartspace.uitemplatedata.SubListTemplateData" ],
  "variables" : [ {
    "name" : "mSubListIcon",
    "type" : "Icon",
    "comment" : "",
    "links" : [ ]
  }, {
    "name" : "mSubListTexts",
    "type" : "List<Text>",
    "comment" : "",
    "links" : [ ]
  }, {
    "name" : "mSubListAction",
    "type" : "TapAction",
    "comment" : "",
    "links" : [ ]
  } ],
  "methods" : [ {
    "name" : "public Builder setSubListIcon(@NonNull Icon subListIcon)",
    "returnType" : "Builder",
    "comment" : "\n         * Sets the sub-list card icon.\n         ",
    "links" : [ ]
  }, {
    "name" : "public Builder setSubListAction(@NonNull TapAction subListAction)",
    "returnType" : "Builder",
    "comment" : "\n         * Sets the card tap action.\n         ",
    "links" : [ ]
  }, {
    "name" : "public SubListTemplateData build()",
    "returnType" : "SubListTemplateData",
    "comment" : "\n         * Builds a new SmartspaceSubListUiTemplateData instance.\n         ",
    "links" : [ ]
  } ],
  "methodNames" : [ "public Builder setSubListIcon(@NonNull Icon subListIcon)", "public Builder setSubListAction(@NonNull TapAction subListAction)", "public SubListTemplateData build()" ],
  "variableNames" : [ "mSubListIcon", "mSubListTexts", "mSubListAction" ]
}