{
  "filePath" : "/home/maryam/clearblue/files/android-source-35/android/app/appsearch/GetByDocumentIdRequest.java",
  "packageName" : "android.app.appsearch",
  "className" : "Builder",
  "comment" : " Builder for {@link GetByDocumentIdRequest} objects. ",
  "links" : [ "android.app.appsearch.GetByDocumentIdRequest" ],
  "variables" : [ {
    "name" : "mNamespace",
    "type" : "String",
    "comment" : "",
    "links" : [ ]
  }, {
    "name" : "mIds",
    "type" : "List<String>",
    "comment" : "",
    "links" : [ ]
  }, {
    "name" : "mProjectionTypePropertyPaths",
    "type" : "Bundle",
    "comment" : "",
    "links" : [ ]
  }, {
    "name" : "mBuilt",
    "type" : "boolean",
    "comment" : "",
    "links" : [ ]
  } ],
  "methods" : [ {
    "name" : "public Builder addIds(@NonNull String... ids)",
    "returnType" : "Builder",
    "comment" : " Adds one or more document IDs to the request. ",
    "links" : [ ]
  }, {
    "name" : "public Builder addIds(@NonNull Collection<String> ids)",
    "returnType" : "Builder",
    "comment" : " Adds a collection of IDs to the request. ",
    "links" : [ ]
  }, {
    "name" : "public Builder addProjection(@NonNull String schemaType, @NonNull Collection<String> propertyPaths)",
    "returnType" : "Builder",
    "comment" : "\n         * Adds property paths for the specified type to be used for projection. If property paths\n         * are added for a type, then only the properties referred to will be retrieved for results\n         * of that type. If a property path that is specified isn't present in a result, it will be\n         * ignored for that result. Property paths cannot be null.\n         *\n         * <p>If no property paths are added for a particular type, then all properties of results\n         * of that type will be retrieved.\n         *\n         * <p>If property path is added for the {@link\n         * GetByDocumentIdRequest#PROJECTION_SCHEMA_TYPE_WILDCARD}, then those property paths will\n         * apply to all results, excepting any types that have their own, specific property paths\n         * set.\n         *\n         * @see SearchSpec.Builder#addProjectionPaths\n         ",
    "links" : [ "android.app.appsearch.GetByDocumentIdRequest#PROJECTION_SCHEMA_TYPE_WILDCARD" ]
  }, {
    "name" : "public Builder addProjectionPaths(@NonNull String schemaType, @NonNull Collection<PropertyPath> propertyPaths)",
    "returnType" : "Builder",
    "comment" : "\n         * Adds property paths for the specified type to be used for projection. If property paths\n         * are added for a type, then only the properties referred to will be retrieved for results\n         * of that type. If a property path that is specified isn't present in a result, it will be\n         * ignored for that result. Property paths cannot be null.\n         *\n         * <p>If no property paths are added for a particular type, then all properties of results\n         * of that type will be retrieved.\n         *\n         * <p>If property path is added for the {@link\n         * GetByDocumentIdRequest#PROJECTION_SCHEMA_TYPE_WILDCARD}, then those property paths will\n         * apply to all results, excepting any types that have their own, specific property paths\n         * set.\n         *\n         * @see SearchSpec.Builder#addProjectionPaths\n         ",
    "links" : [ "android.app.appsearch.GetByDocumentIdRequest#PROJECTION_SCHEMA_TYPE_WILDCARD" ]
  }, {
    "name" : "public GetByDocumentIdRequest build()",
    "returnType" : "GetByDocumentIdRequest",
    "comment" : " Builds a new {@link GetByDocumentIdRequest}. ",
    "links" : [ "android.app.appsearch.GetByDocumentIdRequest" ]
  }, {
    "name" : "private void resetIfBuilt()",
    "returnType" : "void",
    "comment" : "",
    "links" : [ ]
  } ],
  "methodNames" : [ "public Builder addIds(@NonNull String... ids)", "public Builder addIds(@NonNull Collection<String> ids)", "public Builder addProjection(@NonNull String schemaType, @NonNull Collection<String> propertyPaths)", "public Builder addProjectionPaths(@NonNull String schemaType, @NonNull Collection<PropertyPath> propertyPaths)", "public GetByDocumentIdRequest build()", "private void resetIfBuilt()" ],
  "variableNames" : [ "mNamespace", "mIds", "mProjectionTypePropertyPaths", "mBuilt" ]
}