{
  "filePath" : "/home/maryam/clearblue/files/android-source-35/android/service/textclassifier/TextClassifierService.java",
  "packageName" : "android.service.textclassifier",
  "className" : "Callback",
  "comment" : "\n     * Callbacks for TextClassifierService results.\n     *\n     * @param <T> the type of the result\n     ",
  "links" : [ ],
  "variables" : [ ],
  "methods" : [ {
    "name" : " void onSuccess(T result)",
    "returnType" : "void",
    "comment" : "\n         * Returns the result.\n         ",
    "links" : [ ]
  }, {
    "name" : " void onFailure(@NonNull CharSequence error)",
    "returnType" : "void",
    "comment" : "\n         * Signals a failure.\n         ",
    "links" : [ ]
  } ],
  "methodNames" : [ " void onSuccess(T result)", " void onFailure(@NonNull CharSequence error)" ],
  "variableNames" : [ ]
}