{
  "filePath" : "/home/maryam/clearblue/files/android-source-35/android/media/browse/MediaBrowser.java",
  "packageName" : "android.media.browse",
  "className" : "ConnectionCallback",
  "comment" : "\n     * Callbacks for connection related events.\n     ",
  "links" : [ ],
  "variables" : [ ],
  "methods" : [ {
    "name" : "public void onConnected()",
    "returnType" : "void",
    "comment" : "\n         * Invoked after {@link MediaBrowser#connect()} when the request has successfully completed.\n         ",
    "links" : [ "android.media.browse.MediaBrowser#connect()" ]
  }, {
    "name" : "public void onConnectionSuspended()",
    "returnType" : "void",
    "comment" : "\n         * Invoked when the client is disconnected from the media browser.\n         ",
    "links" : [ ]
  }, {
    "name" : "public void onConnectionFailed()",
    "returnType" : "void",
    "comment" : "\n         * Invoked when the connection to the media browser failed.\n         ",
    "links" : [ ]
  }, {
    "name" : "public void onDisconnected()",
    "returnType" : "void",
    "comment" : " the need arises.",
    "links" : [ ]
  } ],
  "methodNames" : [ "public void onConnected()", "public void onConnectionSuspended()", "public void onConnectionFailed()", "public void onDisconnected()" ],
  "variableNames" : [ ]
}