{
  "filePath" : "/home/maryam/clearblue/files/android-source-35/android/app/AppOpsManager.java",
  "packageName" : "android.app",
  "className" : "OnOpActiveChangedInternalListener",
  "comment" : "\n     * Callback for notification of changes to operation state.\n     * This allows you to see the raw op codes instead of strings.\n     * @hide\n     ",
  "links" : [ ],
  "variables" : [ ],
  "methods" : [ {
    "name" : " void onOpActiveChanged(String op, int uid, String packageName, boolean active)",
    "returnType" : "void",
    "comment" : "",
    "links" : [ ]
  }, {
    "name" : " void onOpActiveChanged(int op, int uid, String packageName, boolean active)",
    "returnType" : "void",
    "comment" : "",
    "links" : [ ]
  }, {
    "name" : " void onOpActiveChanged(int op, int uid, String packageName, int virtualDeviceId, boolean active)",
    "returnType" : "void",
    "comment" : "",
    "links" : [ ]
  } ],
  "methodNames" : [ " void onOpActiveChanged(String op, int uid, String packageName, boolean active)", " void onOpActiveChanged(int op, int uid, String packageName, boolean active)", " void onOpActiveChanged(int op, int uid, String packageName, int virtualDeviceId, boolean active)" ],
  "variableNames" : [ ]
}