{
  "filePath" : "/home/maryam/clearblue/files/android-source-35/java/lang/invoke/ByteArrayViewVarHandle.java",
  "packageName" : "java.lang.invoke",
  "className" : "ByteArrayViewVarHandle",
  "comment" : "\n * A VarHandle to access byte array elements as an array of primitive types.\n * @hide\n ",
  "links" : [ ],
  "variables" : [ {
    "name" : "nativeByteOrder",
    "type" : "boolean",
    "comment" : "",
    "links" : [ ]
  } ],
  "methods" : [ {
    "name" : " static ByteArrayViewVarHandle create(Class<?> arrayClass, ByteOrder byteOrder)",
    "returnType" : "ByteArrayViewVarHandle",
    "comment" : "",
    "links" : [ ]
  } ],
  "methodNames" : [ " static ByteArrayViewVarHandle create(Class<?> arrayClass, ByteOrder byteOrder)" ],
  "variableNames" : [ "nativeByteOrder" ]
}